network_check_tool/__init__.py
network_check_tool/app.py
network_check_tool/cli.py
network_check_tool/config/__init__.py
network_check_tool/config/config.py
network_check_tool/models/__init__.py
network_check_tool/models/ping_result.py
network_check_tool/services/__init__.py
network_check_tool/services/ping_service.py
network_check_tool/services/scheduler_service.py
network_check_tool/templates/dashboard.html
network_check_tool/views/__init__.py
network_check_tool/views/dashboard.py
network_check_tool-0.0.2.dist-info/LICENSE
network_check_tool-0.0.2.dist-info/METADATA
network_check_tool-0.0.2.dist-info/WHEEL
network_check_tool-0.0.2.dist-info/entry_points.txt
network_check_tool-0.0.2.dist-info/RECORD
