Metadata-Version: 2.1
Name: network-check-tool
Version: 0.0.2
Summary: A network monitoring tool with ping tracking and dashboard visualization
Home-page: https://github.com/hardwork9047/network-checker
License: MIT
Author: hardwork9047
Author-email: tomatosimple1104@gmail.com
Requires-Python: >=3.10,<4.0
Classifier: License :: OSI Approved :: MIT License
Classifier: Programming Language :: Python :: 3
Classifier: Programming Language :: Python :: 3.10
Classifier: Programming Language :: Python :: 3.11
Classifier: Programming Language :: Python :: 3.12
Classifier: Programming Language :: Python :: 3.13
Requires-Dist: apscheduler (>=3.10.4,<4.0.0)
Requires-Dist: click (>=8.1.3,<9.0.0)
Requires-Dist: flask (>=3.1.0,<4.0.0)
Requires-Dist: flask-cors (>=4.0.0,<5.0.0)
Requires-Dist: flask-sqlalchemy (>=3.1.1,<4.0.0)
Requires-Dist: pandas (>=2.2.3,<3.0.0)
Requires-Dist: ping3 (>=4.0.4,<5.0.0)
Requires-Dist: plotly (>=5.17.0,<6.0.0)
Requires-Dist: toml (>=0.10.2,<0.11.0)
Project-URL: Documentation, https://github.com/hardwork9047/network-checker
Project-URL: Repository, https://github.com/hardwork9047/network-checker
